scrapers/__init__.py
scrapers/base_feed_scraper.py
scrapers/base_parser.py
scrapers/config.toml
scrapers/malawi24.py
scrapers/malawi_voice.py
scrapers/maravi_post.py
scrapers/mwnation.py
scrapers/pij.py
malawi_news_scraper-1.2.0.dist-info/LICENSE
malawi_news_scraper-1.2.0.dist-info/METADATA
malawi_news_scraper-1.2.0.dist-info/WHEEL
malawi_news_scraper-1.2.0.dist-info/top_level.txt
malawi_news_scraper-1.2.0.dist-info/RECORD
