Metadata-Version: 2.1
Name: malawi-news-scraper
Version: 1.2.0
Summary: Scrape news from known news outlets in Malawi
Author-email: Hopson Gausi <hopgausi@gmail.com>
License: MIT License
Project-URL: Homepage, https://github.com/hopgausi/malawi-news-scraper
Keywords: News scraper,scraper,malawi
Classifier: License :: OSI Approved :: MIT License
Classifier: Programming Language :: Python
Classifier: Programming Language :: Python :: 3
Requires-Python: >=3.11
License-File: LICENSE
Requires-Dist: feedparser (>=1.2.0)
Requires-Dist: html2text
Requires-Dist: beautifulsoup4
Provides-Extra: dev
Requires-Dist: black ; extra == 'dev'
Requires-Dist: bumpver ; extra == 'dev'
Requires-Dist: isort ; extra == 'dev'
Requires-Dist: pip-tools ; extra == 'dev'
Requires-Dist: pytest ; extra == 'dev'
